Metadata-Version: 2.1
Name: datasette-render-timestamps
Version: 1.0.1
Summary: Datasette plugin for rendering timestamps
Home-page: https://github.com/simonw/datasette-render-timestamps
Author: Simon Willison
License: Apache License, Version 2.0
Platform: UNKNOWN
Requires-Dist: datasette
Provides-Extra: test
Requires-Dist: pytest ; extra == 'test'
